./.gitignore
./PKG-INFO
./README.md
./pyproject.toml
./release
./lmbl/__init__.py
./lmbl/main.py
learn_music_by_listening-2.0.0.dist-info/METADATA
learn_music_by_listening-2.0.0.dist-info/WHEEL
learn_music_by_listening-2.0.0.dist-info/entry_points.txt
learn_music_by_listening-2.0.0.dist-info/RECORD
