Metadata-Version: 2.4
Name: learn-music-by-listening
Version: 2.0.0
Summary: Learn Music By Listening - Educational music player with facts
Project-URL: Homepage, https://github.com/talwrii/lmbl
Project-URL: Repository, https://github.com/talwrii/lmbl
Project-URL: Issues, https://github.com/talwrii/lmbl/issues
Author-email: "@readwithai" <talwrii@gmail.com>
License: MIT
Keywords: chord-progressions,education,learning,music,youtube
Classifier: Development Status :: 3 - Alpha
Classifier: Intended Audience :: Education
Classifier: Programming Language :: Python :: 3
Classifier: Programming Language :: Python :: 3.8
Classifier: Programming Language :: Python :: 3.9
Classifier: Programming Language :: Python :: 3.10
Classifier: Programming Language :: Python :: 3.11
Classifier: Programming Language :: Python :: 3.12
Classifier: Topic :: Multimedia :: Sound/Audio :: Players
Requires-Python: >=3.8
Requires-Dist: anthropic>=0.18.0
Requires-Dist: plyer>=2.0.0
Requires-Dist: pygame>=2.0.0
Requires-Dist: pynput>=1.7.0
Requires-Dist: yt-dlp>=2023.0.0
Provides-Extra: dev
Requires-Dist: black>=23.0.0; extra == 'dev'
Requires-Dist: pytest>=7.0.0; extra == 'dev'
Requires-Dist: ruff>=0.1.0; extra == 'dev'
